dheeobs/__init__.py
dheeobs/dhee_logger.py
dheeobs/dhee_loghandler.py
dheeobs-0.1.2.dist-info/METADATA
dheeobs-0.1.2.dist-info/WHEEL
dheeobs-0.1.2.dist-info/top_level.txt
dheeobs-0.1.2.dist-info/RECORD
