Metadata-Version: 2.1
Name: dheeobs
Version: 0.1.2
Summary: Dhee observability client
Author: Datalens
Requires-Dist: requests
